date_extractor.py
DatExtractor-1.0.1.dist-info/LICENSE.txt
DatExtractor-1.0.1.dist-info/METADATA
DatExtractor-1.0.1.dist-info/WHEEL
DatExtractor-1.0.1.dist-info/top_level.txt
DatExtractor-1.0.1.dist-info/RECORD
